routes/__init__.py
routes/base.py
routes/mapper.py
routes/middleware.py
routes/route.py
routes/util.py
Routes-2.5.0.dist-info/LICENSE.txt
Routes-2.5.0.dist-info/METADATA
Routes-2.5.0.dist-info/WHEEL
Routes-2.5.0.dist-info/top_level.txt
Routes-2.5.0.dist-info/RECORD
