Metadata-Version: 2.1
Name: Routes
Version: 2.5.0
Summary: Routing Recognition and Generation Tools
Home-page: https://routes.readthedocs.io/
Author: Ben Bangert
Author-email: ben@groovie.org
License: MIT
Keywords: routes webob dispatch
Platform: UNKNOWN
Classifier: Development Status :: 5 - Production/Stable
Classifier: Intended Audience :: Developers
Classifier: License :: OSI Approved :: MIT License
Classifier: Topic :: Internet :: WWW/HTTP
Classifier: Topic :: Software Development :: Libraries :: Python Modules
Classifier: Programming Language :: Python :: Implementation :: PyPy
Classifier: Programming Language :: Python :: Implementation :: CPython
Classifier: Programming Language :: Python
Classifier: Programming Language :: Python :: 2
Classifier: Programming Language :: Python :: 2.7
Classifier: Programming Language :: Python :: 3
Classifier: Programming Language :: Python :: 3.5
Classifier: Programming Language :: Python :: 3.6
Requires-Dist: repoze.lru (>=0.3)
Requires-Dist: six
Provides-Extra: docs
Requires-Dist: Sphinx ; extra == 'docs'
Requires-Dist: webob ; extra == 'docs'
Provides-Extra: middleware
Requires-Dist: webob ; extra == 'middleware'
